{"is_source_file": true, "format": "JavaScript", "description": "This file is a configuration script for Create React App (CRA) using CRACO to customize the Webpack configuration without ejecting. It specifically disables CSS minimization by removing CssMinimizerPlugin from Webpack's minimizer array.", "external_files": ["css-minimizer-webpack-plugin"], "external_methods": ["require"], "published": [], "classes": [], "methods": ["configure"], "calls": ["require('css-minimizer-webpack-plugin')", "webpackConfig.optimization.minimizer.filter()", "webpackConfig.plugins.filter()"], "search-terms": ["craco", "webpack", "CssMinimizerPlugin", "configuration", "css minimization"], "state": 2, "file_id": 15, "knowledge_revision": 35, "git_revision": "", "ctags": [{"_type": "tag", "name": "CssMinimizerPlugin", "path": "/home/kavia/workspace/code-generation/attendance-management-system-42477-42487/attendance_frontend/craco.config.js", "pattern": "/^const CssMinimizerPlugin = require('css-minimizer-webpack-plugin');$/", "language": "JavaScript", "kind": "constant"}, {"_type": "tag", "name": "configure", "path": "/home/kavia/workspace/code-generation/attendance-management-system-42477-42487/attendance_frontend/craco.config.js", "pattern": "/^    configure: (webpackConfig) => {$/", "language": "JavaScript", "kind": "property", "scope": "module.exports.webpack", "scopeKind": "class"}, {"_type": "tag", "name": "exports", "path": "/home/kavia/workspace/code-generation/attendance-management-system-42477-42487/attendance_frontend/craco.config.js", "pattern": "/^module.exports = {$/", "language": "JavaScript", "kind": "class", "scope": "module", "scopeKind": "class"}, {"_type": "tag", "name": "webpack", "path": "/home/kavia/workspace/code-generation/attendance-management-system-42477-42487/attendance_frontend/craco.config.js", "pattern": "/^  webpack: {$/", "language": "JavaScript", "kind": "class", "scope": "module.exports", "scopeKind": "class"}], "hash": "2e47517a2be0b7c6307193aca18e68bc", "format-version": 4, "code-base-name": "attendance_frontend", "filename": "attendance_frontend/craco.config.js", "fields": [{"name": "configure: (webpackConfig) => {", "scope": "module.exports.webpack", "scopeKind": "class", "description": "unavailable"}], "revision_history": [{"35": ""}]}